flexs/__init__.py
flexs/ensemble.py
flexs/evaluate.py
flexs/explorer.py
flexs/landscape.py
flexs/model.py
flexs/types.py
flexs/baselines/__init__.py
flexs/baselines/explorers/__init__.py
flexs/baselines/explorers/adalead.py
flexs/baselines/explorers/bo.py
flexs/baselines/explorers/cbas_dbas.py
flexs/baselines/explorers/cmaes.py
flexs/baselines/explorers/dqn.py
flexs/baselines/explorers/dyna_ppo.py
flexs/baselines/explorers/genetic_algorithm.py
flexs/baselines/explorers/ppo.py
flexs/baselines/explorers/random.py
flexs/baselines/explorers/environments/__init__.py
flexs/baselines/explorers/environments/dyna_ppo.py
flexs/baselines/explorers/environments/ppo.py
flexs/baselines/models/__init__.py
flexs/baselines/models/adaptive_ensemble.py
flexs/baselines/models/cnn.py
flexs/baselines/models/global_epistasis_model.py
flexs/baselines/models/keras_model.py
flexs/baselines/models/mlp.py
flexs/baselines/models/noisy_abstract_model.py
flexs/baselines/models/sklearn_models.py
flexs/landscapes/__init__.py
flexs/landscapes/additive_aav_packaging.py
flexs/landscapes/bert_gfp.py
flexs/landscapes/rna.py
flexs/landscapes/rosetta.py
flexs/landscapes/tf_binding.py
flexs/landscapes/data/additive_aav_packaging/AAV2_single_subs.json
flexs/landscapes/data/additive_aav_packaging/all_data_clean.csv
flexs/landscapes/data/additive_aav_packaging/landscapes.json
flexs/landscapes/data/additive_aav_packaging/landscapes_450_540.json
flexs/landscapes/data/rosetta/3msi.pdb
flexs/landscapes/data/rosetta/3mx7.pdb
flexs/landscapes/data/tf_binding/ARX_L343Q_R1_8mers.txt
flexs/landscapes/data/tf_binding/ARX_L343Q_R2_8mers.txt
flexs/landscapes/data/tf_binding/ARX_P353L_R1_8mers.txt
flexs/landscapes/data/tf_binding/ARX_P353L_R2_8mers.txt
flexs/landscapes/data/tf_binding/ARX_P353R_R1_8mers.txt
flexs/landscapes/data/tf_binding/ARX_P353R_R2_8mers.txt
flexs/landscapes/data/tf_binding/ARX_R332H_R1_8mers.txt
flexs/landscapes/data/tf_binding/ARX_R332H_R2_8mers.txt
flexs-0.2.8.dist-info/LICENSE
flexs-0.2.8.dist-info/METADATA
flexs-0.2.8.dist-info/WHEEL
flexs-0.2.8.dist-info/top_level.txt
flexs-0.2.8.dist-info/RECORD
